lifecycle/README.md
lifecycle/__init__.py
lifecycle/decommission.py
lifecycle/discovery.py
lifecycle/ipmi_reset.py
lifecycle/lockscreen.py
lifecycle/planned.py
lifecycle/src/common/__init__.py
lifecycle/src/common/update_nomad_config.py
lifecycle/src/decommission/__init__.py
lifecycle/src/decommission/bridge.py
lifecycle/src/decommission/disk_operations.py
lifecycle/src/decommission/hardware.py
lifecycle/src/decommission/system_config.py
lifecycle/src/discovery/__init__.py
lifecycle/src/discovery/associated_bridges.py
lifecycle/src/discovery/available_os.py
lifecycle/src/discovery/bmc.py
lifecycle/src/discovery/cpu_info.py
lifecycle/src/discovery/custom_fields.py
lifecycle/src/discovery/device.py
lifecycle/src/discovery/discovery_runner.py
lifecycle/src/discovery/disk_info.py
lifecycle/src/discovery/documents.py
lifecycle/src/discovery/eco_mode.py
lifecycle/src/discovery/gpu_info.py
lifecycle/src/discovery/interfaces.py
lifecycle/src/discovery/ipmi.py
lifecycle/src/discovery/lifecycle.py
lifecycle/src/discovery/memory.py
lifecycle/src/discovery/netplan.py
lifecycle/src/discovery/oem.py
lifecycle/src/discovery/primary_ips.py
lifecycle/src/discovery/storage_layout_data.yml
lifecycle/src/discovery/storage_layouts.py
lifecycle/src/discovery/tags.py
lifecycle/src/discovery/vault.py
lifecycle/src/discovery/version.py
lifecycle/src/discovery/vrf.py
lifecycle/src/discovery/zabbix.py
lifecycle/src/lockscreen/__init__.py
lifecycle/src/lockscreen/bmc.py
lifecycle/src/lockscreen/hardware.py
lifecycle/src/lockscreen/status.py
lifecycle/src/lockscreen/versions.py
lifecycle/src/planned/__init__.py
lifecycle/src/planned/create_device.py
lifecycle/src/planned/get_macs.py
lifecycle/src/planned/locate_device.py
brokkr_lifecycle-1.0.0.dist-info/METADATA
brokkr_lifecycle-1.0.0.dist-info/WHEEL
brokkr_lifecycle-1.0.0.dist-info/entry_points.txt
brokkr_lifecycle-1.0.0.dist-info/top_level.txt
brokkr_lifecycle-1.0.0.dist-info/RECORD
