Metadata-Version: 2.4
Name: brokkr-lifecycle
Version: 1.0.0
Summary: Brokkr Host Manager Lifecycle Management Package
Author-email: Hydra Host Developers <developers@hydrahost.com>
Project-URL: Homepage, https://gitlab.com/hydrahost-developers/brokkr-bridge/brokkr-host-manager
Project-URL: Repository, https://gitlab.com/hydrahost-developers/brokkr-bridge/brokkr-host-manager.git
Project-URL: Issues, https://gitlab.com/hydrahost-developers/brokkr-bridge/brokkr-host-manager/-/issues
Classifier: Development Status :: 4 - Beta
Classifier: Intended Audience :: System Administrators
Classifier: License :: OSI Approved :: MIT License
Classifier: Operating System :: POSIX :: Linux
Classifier: Programming Language :: Python :: 3
Classifier: Programming Language :: Python :: 3.8
Classifier: Programming Language :: Python :: 3.9
Classifier: Programming Language :: Python :: 3.10
Classifier: Programming Language :: Python :: 3.11
Classifier: Topic :: System :: Systems Administration
Requires-Python: >=3.8
Requires-Dist: aiohttp>=3.9.0
Requires-Dist: httpx>=0.25.0
Requires-Dist: pynetbox>=7.3.0
Requires-Dist: requests>=2.31.0
Requires-Dist: tenacity>=8.2.0
Requires-Dist: zabbix-utils>=1.0.0
Requires-Dist: pyyaml>=6.0.1
Requires-Dist: nvidia-ml-py>=13.580.82
Requires-Dist: pyinstaller>=6.17.0
Provides-Extra: dev
Requires-Dist: pytest>=6.0; extra == "dev"
Requires-Dist: pytest-cov>=2.0; extra == "dev"
Requires-Dist: black>=21.0; extra == "dev"
Requires-Dist: isort>=5.0; extra == "dev"
Requires-Dist: mypy>=0.800; extra == "dev"
